{
  "rules": {
    ".read": "auth != null",
    "tpm_system": {
      ".read": "auth != null",
      "history": {
        ".write": "auth != null && (root.child('tpm_system/users/' + auth.uid + '/role').val() === 'admin' || root.child('tpm_system/users/' + auth.uid).val() === 'admin' || root.child('tpm_system/users/' + auth.uid + '/role').val() === 'auditor' || root.child('tpm_system/users/' + auth.uid).val() === 'auditor')"
      },
      "tasks": {
        ".write": "auth != null"
      },
      "tags": {
        ".write": "auth != null"
      },
      "kaizenComments": {
        ".write": "auth != null"
      },
      "users": {
        ".read": "auth != null",
        "$uid": {
          ".write": "auth != null && (auth.uid === $uid || root.child('tpm_system/users/' + auth.uid + '/role').val() === 'admin' || root.child('tpm_system/users/' + auth.uid).val() === 'admin')"
        }
      },
      "points": {
        ".write": "auth != null"
      },
      "logs": {
        ".write": "auth != null"
      }
    }
  }
}